<?xml version="1.0" encoding="UTF-8"?>
<extension name="com_communitysurveys" type="cjblog_points" method="upgrade">
	<extension_rule>
		<rule_name>com_communitysurveys.credits</rule_name>
		<rule_title>Survey Response Credits</rule_title>
		<rule_description>Points charged to survey creator for each survey response received.</rule_description>
		<auto_approve>1</auto_approve>
		<asset_name>com_communitysurveys</asset_name>
		<access_level>1</access_level>
	</extension_rule>
	
	<extension_rule>
		<rule_name>com_communitysurveys.new_survey</rule_name>
		<rule_title>New Survey</rule_title>
		<rule_description>Points awarded for creating a survey.</rule_description>
		<auto_approve>1</auto_approve>
		<asset_name>com_communitysurveys</asset_name>
		<access_level>1</access_level>
	</extension_rule>
	
	<extension_rule>
		<rule_name>com_communitysurveys.survey_response</rule_name>
		<rule_title>Survey Response Award</rule_title>
		<rule_description>Points awarded for responding to a survey.</rule_description>
		<auto_approve>1</auto_approve>
		<asset_name>com_communitysurveys</asset_name>
		<access_level>1</access_level>
	</extension_rule>
</extension>